odoo8_addon_website_snippet_anchor-8.0.1.0.0.99.dev18-py2.7-nspkg.pth
odoo8_addon_website_snippet_anchor-8.0.1.0.0.99.dev18.dist-info/DESCRIPTION.rst
odoo8_addon_website_snippet_anchor-8.0.1.0.0.99.dev18.dist-info/METADATA
odoo8_addon_website_snippet_anchor-8.0.1.0.0.99.dev18.dist-info/RECORD
odoo8_addon_website_snippet_anchor-8.0.1.0.0.99.dev18.dist-info/WHEEL
odoo8_addon_website_snippet_anchor-8.0.1.0.0.99.dev18.dist-info/metadata.json
odoo8_addon_website_snippet_anchor-8.0.1.0.0.99.dev18.dist-info/namespace_packages.txt
odoo8_addon_website_snippet_anchor-8.0.1.0.0.99.dev18.dist-info/top_level.txt
odoo_addons/website_snippet_anchor/README.rst
odoo_addons/website_snippet_anchor/__init__.py
odoo_addons/website_snippet_anchor/__openerp__.py
odoo_addons/website_snippet_anchor/i18n/af.po
odoo_addons/website_snippet_anchor/i18n/ar.po
odoo_addons/website_snippet_anchor/i18n/bg.po
odoo_addons/website_snippet_anchor/i18n/bs.po
odoo_addons/website_snippet_anchor/i18n/ca.po
odoo_addons/website_snippet_anchor/i18n/cs.po
odoo_addons/website_snippet_anchor/i18n/da.po
odoo_addons/website_snippet_anchor/i18n/de.po
odoo_addons/website_snippet_anchor/i18n/el.po
odoo_addons/website_snippet_anchor/i18n/el_GR.po
odoo_addons/website_snippet_anchor/i18n/en_GB.po
odoo_addons/website_snippet_anchor/i18n/es.po
odoo_addons/website_snippet_anchor/i18n/es_AR.po
odoo_addons/website_snippet_anchor/i18n/es_CL.po
odoo_addons/website_snippet_anchor/i18n/es_CO.po
odoo_addons/website_snippet_anchor/i18n/es_CR.po
odoo_addons/website_snippet_anchor/i18n/es_DO.po
odoo_addons/website_snippet_anchor/i18n/es_EC.po
odoo_addons/website_snippet_anchor/i18n/es_MX.po
odoo_addons/website_snippet_anchor/i18n/es_PE.po
odoo_addons/website_snippet_anchor/i18n/es_PY.po
odoo_addons/website_snippet_anchor/i18n/es_VE.po
odoo_addons/website_snippet_anchor/i18n/et.po
odoo_addons/website_snippet_anchor/i18n/eu.po
odoo_addons/website_snippet_anchor/i18n/fa.po
odoo_addons/website_snippet_anchor/i18n/fi.po
odoo_addons/website_snippet_anchor/i18n/fr.po
odoo_addons/website_snippet_anchor/i18n/fr_CA.po
odoo_addons/website_snippet_anchor/i18n/gl.po
odoo_addons/website_snippet_anchor/i18n/he.po
odoo_addons/website_snippet_anchor/i18n/hr.po
odoo_addons/website_snippet_anchor/i18n/hr_HR.po
odoo_addons/website_snippet_anchor/i18n/hu.po
odoo_addons/website_snippet_anchor/i18n/id.po
odoo_addons/website_snippet_anchor/i18n/it.po
odoo_addons/website_snippet_anchor/i18n/ja.po
odoo_addons/website_snippet_anchor/i18n/ka.po
